tangram/__init__.abi3.so
tangram/py.typed
tangram/__init__.pyi
tangram-0.7.0.dist-info/top_level.txt
tangram-0.7.0.dist-info/METADATA
tangram-0.7.0.dist-info/RECORD
tangram-0.7.0.dist-info/LICENSE
tangram-0.7.0.dist-info/WHEEL
