Metadata-Version: 2.1
Name: tangram
Version: 0.7.0
Summary: Tangram for Python
Home-page: https://www.tangram.dev
Author: Tangram
Author-email: root@tangram.dev
License: UNKNOWN
Platform: UNKNOWN
Classifier: Programming Language :: Python
Classifier: License :: OSI Approved :: MIT License
Classifier: Operating System :: OS Independent
License-File: LICENSE
